felindra/__init__.py
felindra/__main__.py
felindra/certificate.py
felindra/constants.py
felindra/etc/share/ca-anafi-ai.pem
felindra/felindra_main.py
felindra/libfelindra.py
felindra/resource.py
felindra/tools.py
felindra/webclient.py
parrot_felindra-7.4.0.dist-info/entry_points.txt
parrot_felindra-7.4.0.dist-info/LICENSE.md
parrot_felindra-7.4.0.dist-info/WHEEL
parrot_felindra-7.4.0.dist-info/METADATA
parrot_felindra-7.4.0.dist-info/RECORD
