Metadata-Version: 2.1
Name: parrot-felindra
Version: 7.4.0
Summary: Parrot Media Signature Verifier tool
License: BSD-3-Clause
Author: Mathieu Le Mauff
Author-email: mathieu.lemauff@parrot.com
Requires-Python: >=3.8,<4.0
Classifier: Development Status :: 4 - Beta
Classifier: Intended Audience :: Developers
Classifier: Intended Audience :: Education
Classifier: Intended Audience :: Science/Research
Classifier: License :: OSI Approved
Classifier: License :: OSI Approved :: BSD License
Classifier: Operating System :: POSIX :: Linux
Classifier: Programming Language :: C
Classifier: Programming Language :: Python
Classifier: Programming Language :: Python :: 3
Classifier: Programming Language :: Python :: 3.10
Classifier: Programming Language :: Python :: 3.8
Classifier: Programming Language :: Python :: 3.9
Classifier: Topic :: Scientific/Engineering
Requires-Dist: cryptography
Requires-Dist: pycryptodome
Requires-Dist: requests
